{
  "items": [
    {
      "id": "OHqsQwFrKO0C",
      "volumeInfo": {
        "title": "Loves Music, Loves to Dance",
        "authors": [
          "Mary Higgins Clark"
        ],
        "publishedDate": "1992-03",
        "pageCount": 339,
        "categories": [
          "Fiction"
        ],
        "averageRating": 5,
        "ratingsCount": 1
      }
    },
    {
      "id": "bIZiAAAAMAAJ",
      "volumeInfo": {
        "title": "A Game of Thrones",
        "authors": [
          "George R. R. Martin"
        ],
        "publishedDate": "2011",
        "pageCount": 876,
        "categories": [
          "Fiction"
        ],
        "averageRating": 4.5,
        "ratingsCount": 130
      }
    },
    {
      "id": "gGWvDUUi58cC",
      "volumeInfo": {
        "title": "Tuesday",
        "authors": [
          "David Wiesner"
        ],
        "publishedDate": "1991",
        "pageCount": 36,
        "categories": [
          "Juvenile Fiction"
        ],
        "averageRating": 3,
        "ratingsCount": 6
      }
    },
    {
      "id": "ACMYLqk_7GoC",
      "volumeInfo": {
        "title": "And Then There Were None",
        "authors": [
          "Agatha Christie"
        ],
        "publishedDate": "2001-05-13",
        "pageCount": 294,
        "categories": [
          "Fiction"
        ],
        "averageRating": 4,
        "ratingsCount": 41
      }
    },
    {
      "id": "KmBnH5U_GgoC",
      "volumeInfo": {
        "title": "Fractured",
        "authors": [
          "Karin Slaughter"
        ],
        "publishedDate": "2009-06-23",
        "pageCount": 530,
        "categories": [
          "Abused wives"
        ]
      }
    },
    {
      "id": "4qVGAFRByvIC",
      "volumeInfo": {
        "title": "A Time to Kill",
        "authors": [
          "John Grisham"
        ],
        "publishedDate": "1992",
        "pageCount": 530,
        "categories": [
          "Fiction"
        ],
        "averageRating": 3.5,
        "ratingsCount": 3
      }
    },
    {
      "id": "x9BlAAAAMAAJ",
      "volumeInfo": {
        "title": "The Colorado Kid",
        "authors": [
          "Stephen King"
        ],
        "publishedDate": "2005",
        "pageCount": 204,
        "categories": [
          "Fiction"
        ],
        "averageRating": 3,
        "ratingsCount": 8
      }
    },
    {
      "id": "gP3UiUyOTugC",
      "volumeInfo": {
        "title": "The Road to Gandolfo",
        "authors": [
          "Robert Ludlum"
        ],
        "publishedDate": "1992",
        "pageCount": 322,
        "categories": [
          "Adventure stories"
        ]
      }
    },
    {
      "id": "jk0rAQAAIAAJ",
      "volumeInfo": {
        "title": "Mean Spirit",
        "authors": [
          "Linda Hogan"
        ],
        "publishedDate": "1992",
        "pageCount": 398,
        "categories": [
          "Fiction"
        ]
      }
    },
    {
      "id": "ICczBrCNqC0C",
      "volumeInfo": {
        "title": "Plum Lovin'",
        "authors": [
          "Janet Evanovich"
        ],
        "publishedDate": "2008-01-08",
        "pageCount": 292,
        "categories": [
          "Fiction"
        ]
      }
    },
    {
      "id": "35SA8u4QpacC",
      "volumeInfo": {
        "title": "The Runaway Jury",
        "authors": [
          "John Grisham"
        ],
        "publishedDate": "1997",
        "pageCount": 561,
        "categories": [
          "Biloxi (Miss.)"
        ]
      }
    },
    {
      "id": "IuGHDQAAQBAJ",
      "volumeInfo": {
        "title": "Turbo Twenty-three",
        "authors": [
          "Janet Evanovich"
        ],
        "publishedDate": "2016",
        "pageCount": 305,
        "categories": [
          "Fiction"
        ]
      }
    },
    {
      "id": "mFjPpjWO4dUC",
      "volumeInfo": {
        "title": "Still Life",
        "authors": [
          "Louise Penny"
        ],
        "publishedDate": "2007-05",
        "pageCount": 322,
        "categories": [
          "Fiction"
        ]
      }
    },
    {
      "id": "UEAfl4Qwb1AC",
      "volumeInfo": {
        "title": "A Purple Place for Dying",
        "authors": [
          "John Dann MacDonald"
        ],
        "publishedDate": "1995",
        "pageCount": 241,
        "categories": [
          "Detective and mystery stories"
        ]
      }
    },
    {
      "id": "ujXZe244b48C",
      "volumeInfo": {
        "title": "Where are the Children?",
        "authors": [
          "Mary Higgins Clark"
        ],
        "publishedDate": "1992",
        "pageCount": 232,
        "categories": [
          "FICTION"
        ]
      }
    },
    {
      "id": "kjb1P1fJnfcC",
      "volumeInfo": {
        "title": "4.50 from Paddington",
        "authors": [
          "Agatha Christie"
        ],
        "publishedDate": "1987",
        "pageCount": 228,
        "categories": [
          "Fiction"
        ],
        "averageRating": 4,
        "ratingsCount": 8
      }
    },
    {
      "id": "dXccl8vD4LoC",
      "volumeInfo": {
        "title": "The Narrows",
        "authors": [
          "Michael Connelly"
        ],
        "publishedDate": "2005-03",
        "pageCount": 462,
        "categories": [
          "Fiction"
        ],
        "averageRating": 3.5,
        "ratingsCount": 7
      }
    },
    {
      "id": "J8k2csBT-80C",
      "volumeInfo": {
        "title": "A Case of Need",
        "authors": [
          "Michael Crichton",
          "Jeffrey Hudson"
        ],
        "publishedDate": "1969",
        "pageCount": 420,
        "categories": [
          "Fiction"
        ],
        "averageRating": 3.5,
        "ratingsCount": 9
      }
    },
    {
      "id": "OwzXHyR1W-AC",
      "volumeInfo": {
        "title": "Crime and Punishment",
        "authors": [
          "Fyodor Dostoyevsky"
        ],
        "publishedDate": "1953",
        "pageCount": 428,
        "categories": [
          "Murder"
        ]
      }
    },
    {
      "id": "s5ulrjc71nIC",
      "volumeInfo": {
        "title": "The Surgeon",
        "authors": [
          "Tess Gerritsen"
        ],
        "publishedDate": "2001",
        "pageCount": 530,
        "categories": [
          "Fiction"
        ]
      }
    },
    {
      "id": "R6snAQAAMAAJ",
      "volumeInfo": {
        "title": "Murder on the Orient Express",
        "authors": [
          "Agatha Christie"
        ],
        "publishedDate": "1968",
        "pageCount": 264,
        "categories": [
          "Detective and mystery stories"
        ]
      }
    },
    {
      "id": "b8lyy_gQZTkC",
      "volumeInfo": {
        "title": "Every Dead Thing",
        "authors": [
          "John Connolly"
        ],
        "publishedDate": "2009-01-27",
        "pageCount": 484,
        "categories": [
          "Fiction"
        ]
      }
    },
    {
      "id": "SCHqme8AluYC",
      "volumeInfo": {
        "title": "The Invisible Man",
        "authors": [
          "Len Jenkin",
          "Herbert George Wells"
        ],
        "publishedDate": "2000",
        "pageCount": 78,
        "categories": [
          "Drama"
        ]
      }
    },
    {
      "id": "T8i2CYntp6UC",
      "volumeInfo": {
        "title": "Two for the Dough",
        "authors": [
          "Janet Evanovich"
        ],
        "publishedDate": "1996",
        "pageCount": 342,
        "categories": [
          "Fiction"
        ],
        "averageRating": 4,
        "ratingsCount": 4
      }
    },
    {
      "id": "av8SBXdrG7YC",
      "volumeInfo": {
        "title": "Hannibal",
        "authors": [
          "Thomas Harris"
        ],
        "publishedDate": "2000",
        "pageCount": 580,
        "categories": [
          "Dangerously mentally ill"
        ],
        "averageRating": 4.5,
        "ratingsCount": 2
      }
    },
    {
      "id": "KProIPug-OsC",
      "volumeInfo": {
        "title": "Ricochet",
        "authors": [
          "Sandra Brown"
        ],
        "publishedDate": "2006",
        "pageCount": 401,
        "categories": [
          "Authors, American"
        ]
      }
    },
    {
      "id": "HuWP4w41tOEC",
      "volumeInfo": {
        "title": "Brother Odd",
        "authors": [
          "Dean Ray Koontz"
        ],
        "publishedDate": "2007",
        "pageCount": 466,
        "categories": [
          "Abandoned children"
        ],
        "averageRating": 4.5,
        "ratingsCount": 4
      }
    },
    {
      "id": "FUe7l6FoiVIC",
      "volumeInfo": {
        "title": "Muscle Memory",
        "authors": [
          "William G. Tapply"
        ],
        "publishedDate": "2003-04-14",
        "pageCount": 308,
        "categories": [
          "Fiction"
        ]
      }
    },
    {
      "id": "q_Bb4SnE2i0C",
      "volumeInfo": {
        "title": "The Sherwood Ring",
        "authors": [
          "Elizabeth Marie Pope"
        ],
        "publishedDate": "2001",
        "pageCount": 276,
        "categories": [
          "Juvenile Fiction"
        ],
        "averageRating": 5,
        "ratingsCount": 1
      }
    },
    {
      "id": "9iXsIAND7KQC",
      "volumeInfo": {
        "title": "The House at Riverton",
        "authors": [
          "Kate Morton"
        ],
        "publishedDate": "2009-03-03",
        "pageCount": 496,
        "categories": [
          "Fiction"
        ],
        "averageRating": 3,
        "ratingsCount": 1
      }
    },
    {
      "id": "5XDdP-5YxUsC",
      "volumeInfo": {
        "title": "Nine Nights",
        "authors": [
          "Bernardo Carvalho"
        ],
        "publishedDate": "2008",
        "pageCount": 226,
        "categories": [
          "Americans"
        ]
      }
    },
    {
      "id": "FoyhSrj6RFsC",
      "volumeInfo": {
        "title": "The Revenge of the Wizard's Ghost",
        "authors": [
          "John Bellairs"
        ],
        "publishedDate": "1997",
        "pageCount": 164,
        "categories": [
          "Ghosts"
        ]
      }
    },
    {
      "id": "IYZRU3i0m-QC",
      "volumeInfo": {
        "title": "The Rule of Four",
        "authors": [
          "Ian Caldwell",
          "Dustin Thomason"
        ],
        "publishedDate": "2005",
        "pageCount": 626,
        "categories": [
          "Fiction"
        ]
      }
    },
    {
      "id": "SPSn4HdxigkC",
      "volumeInfo": {
        "title": "The Redbreast",
        "authors": [
          "Jo Nesbo"
        ],
        "publishedDate": "2006",
        "pageCount": 532,
        "categories": [
          "Fiction"
        ]
      }
    },
    {
      "id": "vwt6of7puqwC",
      "volumeInfo": {
        "title": "Riverboat Ruse",
        "authors": [
          "Carolyn Keene"
        ],
        "publishedDate": "2005-05",
        "pageCount": 166,
        "categories": [
          "Juvenile Fiction"
        ]
      }
    },
    {
      "id": "fVXhWW7ZRkwC",
      "volumeInfo": {
        "title": "Contest",
        "authors": [
          "Matthew Reilly"
        ],
        "publishedDate": "2005-12-27",
        "pageCount": 452,
        "categories": [
          "Fiction"
        ],
        "averageRating": 4.5,
        "ratingsCount": 3
      }
    },
    {
      "id": "pw4JuAEACAAJ",
      "volumeInfo": {
        "title": "Crime and Punishment",
        "authors": [
          "Fedor Mikhailovich Dostoevskii"
        ],
        "publishedDate": "1968",
        "pageCount": 434,
        "categories": [
          "Murder"
        ]
      }
    },
    {
      "id": "Yg4mDwAAQBAJ",
      "volumeInfo": {
        "title": "True Evil",
        "authors": [
          "Greg Iles"
        ],
        "publishedDate": "2007-09-25",
        "pageCount": 672,
        "categories": [
          "Fiction"
        ]
      }
    },
    {
      "id": "jwDVVUxz7L4C",
      "volumeInfo": {
        "title": "Well-schooled in Murder",
        "authors": [
          "Elizabeth George"
        ],
        "publishedDate": "1991",
        "pageCount": 442,
        "categories": [
          "Detective and mystery stories"
        ]
      }
    },
    {
      "id": "Mt90K-0Jty4C",
      "volumeInfo": {
        "title": "To the Nines",
        "authors": [
          "Janet Evanovich"
        ],
        "publishedDate": "2004-06-14",
        "pageCount": 360,
        "categories": [
          "Fiction"
        ],
        "averageRating": 4,
        "ratingsCount": 16
      }
    }
  ]
}
